pyrea/__init__.py
pyrea/api_tests.py
pyrea/call_c.py
pyrea/core.py
pyrea/debug.py
pyrea/functional.py
pyrea/graph.py
pyrea/hc_fused.py
pyrea/model.py
pyrea/structure.py
pyrea-1.0.12.dist-info/LICENSE
pyrea-1.0.12.dist-info/METADATA
pyrea-1.0.12.dist-info/WHEEL
pyrea-1.0.12.dist-info/top_level.txt
pyrea-1.0.12.dist-info/RECORD
