Metadata-Version: 2.1
Name: pyrea
Version: 1.0.12
Summary: Multi-view clustering with deep ensemble structures.
Home-page: https://github.com/mdbloice/Pyrea
Author: Marcus D. Bloice, Bastian Pfeifer
Author-email: marcus.bloice@medunigraz.at
License: MIT
Keywords: multi-view,clustering,ensemble clustering
Classifier: Development Status :: 4 - Beta
Classifier: Intended Audience :: Science/Research
Classifier: Intended Audience :: Developers
Classifier: License :: OSI Approved :: MIT License
Classifier: Programming Language :: Python
Classifier: Programming Language :: Python :: 3
Classifier: Programming Language :: Python :: 3.6
Classifier: Programming Language :: Python :: 3.7
Classifier: Programming Language :: Python :: 3.8
Classifier: Programming Language :: Python :: 3.9
Classifier: Programming Language :: Python :: 3.10
Classifier: Programming Language :: Python :: 3.11
Classifier: Programming Language :: Python :: 3 :: Only
Classifier: Topic :: Software Development
Classifier: Topic :: Scientific/Engineering
Classifier: Operating System :: Microsoft :: Windows
Classifier: Operating System :: POSIX :: Linux
Classifier: Operating System :: MacOS
Requires-Python: >=3.6
License-File: LICENSE
Requires-Dist: pandas (>0.20.0)
Requires-Dist: numpy (>1.0.0)
Requires-Dist: scikit-learn (>1.1.0)
Requires-Dist: scipy (>1.5.4)
Requires-Dist: deap (>1.3.0)
